Metadata-Version: 2.1
Name: komlib
Version: 0.1
Summary: Kompas python cloud library
Home-page: UNKNOWN
Author: Kompas ML team
Author-email: fatchur.rahman1@gmail.com
License: UNKNOWN
Platform: UNKNOWN
